LICENSE
MANIFEST.in
README.rst
setup.py
gears_handlebars/__init__.py
gears_handlebars/compiler.js
gears_handlebars/compiler.py
gears_handlebars.egg-info/PKG-INFO
gears_handlebars.egg-info/SOURCES.txt
gears_handlebars.egg-info/dependency_links.txt
gears_handlebars.egg-info/top_level.txt
gears_handlebars/node_modules/handlebars/.gitmodules
gears_handlebars/node_modules/handlebars/.istanbul.yml
gears_handlebars/node_modules/handlebars/.npmignore
gears_handlebars/node_modules/handlebars/CONTRIBUTING.md
gears_handlebars/node_modules/handlebars/FAQ.md
gears_handlebars/node_modules/handlebars/LICENSE
gears_handlebars/node_modules/handlebars/README.markdown
gears_handlebars/node_modules/handlebars/package.json
gears_handlebars/node_modules/handlebars/print-script
gears_handlebars/node_modules/handlebars/release-notes.md
gears_handlebars/node_modules/handlebars/runtime.js
gears_handlebars/node_modules/handlebars/bin/handlebars
gears_handlebars/node_modules/handlebars/coverage/coverage.json
gears_handlebars/node_modules/handlebars/coverage/lcov.info
gears_handlebars/node_modules/handlebars/coverage/lcov-report/index.html
gears_handlebars/node_modules/handlebars/coverage/lcov-report/prettify.css
gears_handlebars/node_modules/handlebars/coverage/lcov-report/prettify.js
gears_handlebars/node_modules/handlebars/coverage/lcov-report/dist/cjs/handlebars.js.html
gears_handlebars/node_modules/handlebars/coverage/lcov-report/dist/cjs/handlebars.runtime.js.html
gears_handlebars/node_modules/handlebars/coverage/lcov-report/dist/cjs/index.html
gears_handlebars/node_modules/handlebars/coverage/lcov-report/dist/cjs/handlebars/base.js.html
gears_handlebars/node_modules/handlebars/coverage/lcov-report/dist/cjs/handlebars/exception.js.html
gears_handlebars/node_modules/handlebars/coverage/lcov-report/dist/cjs/handlebars/index.html
gears_handlebars/node_modules/handlebars/coverage/lcov-report/dist/cjs/handlebars/runtime.js.html
gears_handlebars/node_modules/handlebars/coverage/lcov-report/dist/cjs/handlebars/safe-string.js.html
gears_handlebars/node_modules/handlebars/coverage/lcov-report/dist/cjs/handlebars/utils.js.html
